pugh_torch/__init__.py
pugh_torch/exceptions.py
pugh_torch/helpers.py
pugh_torch/augmentations/__init__.py
pugh_torch/augmentations/transforms/__init__.py
pugh_torch/augmentations/transforms/resize_shortest.py
pugh_torch/callbacks/__init__.py
pugh_torch/callbacks/model_checkpoint.py
pugh_torch/callbacks/tensorboard_add_classification.py
pugh_torch/callbacks/tensorboard_add_ss.py
pugh_torch/callbacks/tensorboard_base.py
pugh_torch/datasets/__init__.py
pugh_torch/datasets/base.py
pugh_torch/datasets/torchvision.py
pugh_torch/datasets/classification/__init__.py
pugh_torch/datasets/classification/cifar.py
pugh_torch/datasets/classification/imagenet.py
pugh_torch/datasets/classification/mnist.py
pugh_torch/datasets/segmentation/__init__.py
pugh_torch/datasets/segmentation/ade20k.py
pugh_torch/losses/__init__.py
pugh_torch/losses/hetero_cross_entropy.py
pugh_torch/losses/label_smoothing.py
pugh_torch/mappings/__init__.py
pugh_torch/mappings/color.py
pugh_torch/metrics/__init__.py
pugh_torch/models/__init__.py
pugh_torch/models/resnet.py
pugh_torch/modules/__init__.py
pugh_torch/modules/activation.py
pugh_torch/modules/conv.py
pugh_torch/modules/init.py
pugh_torch/modules/lightning_module.py
pugh_torch/modules/load_state_dict_mixin.py
pugh_torch/optimizers/__init__.py
pugh_torch/optimizers/base.py
pugh_torch/optimizers/lookahead.py
pugh_torch/optimizers/ralamb.py
pugh_torch/optimizers/rangerlars.py
pugh_torch/transforms/__init__.py
pugh_torch/transforms/imagenet.py
pugh_torch/utils/__init__.py
pugh_torch/utils/tensorboard.py
pugh_torch-0.4.0.dist-info/LICENSE
pugh_torch-0.4.0.dist-info/METADATA
pugh_torch-0.4.0.dist-info/WHEEL
pugh_torch-0.4.0.dist-info/top_level.txt
pugh_torch-0.4.0.dist-info/RECORD
